password_mixin/__init__.py
password_mixin/errors.py
password_mixin/mixin.py
password_mixin-0.1.3.dist-info/LICENSE
password_mixin-0.1.3.dist-info/METADATA
password_mixin-0.1.3.dist-info/WHEEL
password_mixin-0.1.3.dist-info/top_level.txt
password_mixin-0.1.3.dist-info/RECORD
