Metadata-Version: 2.1
Name: password-mixin
Version: 0.1.3
Summary: Mixin that adds useful password methods to your Python objects
Home-page: https://github.com/joegasewicz/password-mixin
Author: Joe Gasewicz
Author-email: joegasewicz@gmail.com
License: UNKNOWN
Platform: UNKNOWN
Classifier: Programming Language :: Python :: 3.4
Classifier: Programming Language :: Python :: 3.5
Classifier: Programming Language :: Python :: 3.6
Classifier: Programming Language :: Python :: 3.7
Classifier: Programming Language :: Python :: 3.8
Classifier: Programming Language :: Python :: 3.9
Classifier: License :: OSI Approved :: GNU General Public License v3 or later (GPLv3+)
Classifier: Operating System :: OS Independent
